{"name":"TTools","tagline":"TwitterTools Library","body":"ttools 2.0\r\n======\r\n\r\nTTools (Twitter Tools) Library aims to make life easier for twitter app developers, providing a simple workflow for authentication, while maintaining a high-level of flexibility for various types of applications.\r\n\r\nInstallation via composer\r\n=====\r\n\r\nAdd this requirement to your composer.json file:\r\n\r\n<pre>\r\n{\r\n    \"require\": {\r\n            \"ttools/ttools\": \"dev-master\"\r\n    }\r\n}\r\n\r\n</pre>\r\n\r\n\r\nexamples\r\n=====\r\n\r\n- [Basic Usage - single user Application](https://github.com/ttools/ttools/blob/master/doc/basic_singleuser.rst)\r\n- [Basic multi-user (with auth) Application](https://github.com/ttools/ttools/blob/master/doc/basic_multiuser.rst)\r\n\r\ndemos\r\n=====\r\n\r\n\r\n<a href=\"https://github.com/erikaheidi/ttools-demos\">https://github.com/erikaheidi/ttools-demos</a>\r\n","google":"UA-39863705-1","note":"Don't delete this file! It's used internally to help with page regeneration."}